ltcodecs/__init__.py
ltcodecs/bool_codec.py
ltcodecs/bytes_codec.py
ltcodecs/ccl_latlon_bcd_codec.py
ltcodecs/ccl_latlon_codec.py
ltcodecs/exceptions.py
ltcodecs/exponentialgolomb_integer_codec.py
ltcodecs/field_codec.py
ltcodecs/fixed_len_array_codec.py
ltcodecs/fixedint_codec.py
ltcodecs/float_codec.py
ltcodecs/ieee_float_codec.py
ltcodecs/linspace_float_codec.py
ltcodecs/lzma_codec.py
ltcodecs/multiple_field_codec.py
ltcodecs/optional_field_codec.py
ltcodecs/padding_codec.py
ltcodecs/ros_message_codec.py
ltcodecs/ros_msg_field_codec.py
ltcodecs/rostime_codec.py
ltcodecs/string_codecs.py
ltcodecs/string_enum_codec.py
ltcodecs/variable_len_array_codec.py
ltcodecs/varint_codec.py
ltcodecs-4.2.1.dist-info/licenses/LICENSE
ltcodecs-4.2.1.dist-info/METADATA
ltcodecs-4.2.1.dist-info/WHEEL
ltcodecs-4.2.1.dist-info/top_level.txt
ltcodecs-4.2.1.dist-info/RECORD
