Metadata-Version: 2.4
Name: ltcodecs
Version: 4.2.1
Summary: LT Codecs: Lightweight codecs for use over low-throughput links
Author: Woods Hole Oceanographic Institution, Acoustic Communications Group
License: LGPL-3.0-or-later
Project-URL: homepage, https://git.whoi.edu/acomms/ltcodec/
Project-URL: documentation, https://acomms.pages.whoi.edu/ltcodec/
Keywords: Library,Python Modules,Scientific/Engineering
Classifier: Development Status :: 5 - Production/Stable
Classifier: Intended Audience :: Developers
Classifier: Intended Audience :: Science/Research
Classifier: Topic :: Software Development :: Libraries :: Python Modules
Classifier: Topic :: Scientific/Engineering
Requires-Python: >=3.6
License-File: LICENSE
Requires-Dist: armw
Requires-Dist: bitstring
Requires-Dist: msgpack
Requires-Dist: crccheck
Requires-Dist: rospy-yaml-include
Dynamic: license-file
